{
    "leaver_status": {
        "0": {
            "games": 5667,
            "win": 2992
        },
        "1": {
            "games": 104,
            "win": 10
        },
        "2": {
            "games": 40,
            "win": 12
        },
        "3": {
            "games": 8,
            "win": 1
        },
        "4": {
            "games": 5,
            "win": 1
        }
    },
    "game_mode": {
        "1": {
            "games": 419,
            "win": 211
        },
        "2": {
            "games": 74,
            "win": 51
        },
        "4": {
            "games": 157,
            "win": 83
        },
        "5": {
            "games": 21,
            "win": 15
        },
        "22": {
            "games": 5153,
            "win": 2656
        }
    },
    "lobby_type": {
        "0": {
            "games": 727,
            "win": 370
        },
        "7": {
            "games": 5068,
            "win": 2623
        },
        "9": {
            "games": 29,
            "win": 23
        }
    },
    "lane_role": {
        "0": {
            "games": 4984,
            "win": 2589
        },
        "1": {
            "games": 235,
            "win": 113
        },
        "2": {
            "games": 326,
            "win": 162
        },
        "3": {
            "games": 263,
            "win": 143
        },
        "4": {
            "games": 16,
            "win": 9
        }
    },
    "region": {
        "1": {
            "games": 1,
            "win": 0
        },
        "2": {
            "games": 2,
            "win": 0
        },
        "3": {
            "games": 2182,
            "win": 1143
        },
        "8": {
            "games": 2658,
            "win": 1353
        },
        "9": {
            "games": 981,
            "win": 520
        }
    },
    "patch": {
        "11": {
            "games": 153,
            "win": 70
        },
        "12": {
            "games": 6,
            "win": 5
        },
        "13": {
            "games": 272,
            "win": 143
        },
        "14": {
            "games": 477,
            "win": 271
        },
        "15": {
            "games": 146,
            "win": 77
        },
        "16": {
            "games": 111,
            "win": 61
        },
        "17": {
            "games": 70,
            "win": 37
        },
        "18": {
            "games": 565,
            "win": 288
        },
        "19": {
            "games": 43,
            "win": 24
        },
        "20": {
            "games": 203,
            "win": 104
        },
        "21": {
            "games": 121,
            "win": 56
        },
        "22": {
            "games": 36,
            "win": 19
        },
        "23": {
            "games": 47,
            "win": 20
        },
        "24": {
            "games": 304,
            "win": 159
        },
        "25": {
            "games": 784,
            "win": 413
        },
        "26": {
            "games": 376,
            "win": 184
        },
        "27": {
            "games": 52,
            "win": 25
        },
        "28": {
            "games": 57,
            "win": 35
        },
        "29": {
            "games": 31,
            "win": 15
        },
        "30": {
            "games": 39,
            "win": 26
        },
        "31": {
            "games": 37,
            "win": 19
        },
        "33": {
            "games": 138,
            "win": 60
        },
        "34": {
            "games": 2,
            "win": 1
        },
        "35": {
            "games": 49,
            "win": 31
        },
        "36": {
            "games": 51,
            "win": 26
        },
        "37": {
            "games": 92,
            "win": 41
        },
        "38": {
            "games": 429,
            "win": 223
        },
        "39": {
            "games": 366,
            "win": 197
        },
        "40": {
            "games": 327,
            "win": 157
        },
        "41": {
            "games": 434,
            "win": 227
        },
        "42": {
            "games": 6,
            "win": 2
        }
    },
    "is_radiant": {
        "0": {
            "games": 2880,
            "win": 1438
        },
        "1": {
            "games": 2944,
            "win": 1578
        }
    }
}