[
{
"match_id": 5168286986,
"player_slot": 1,
"radiant_win": false,
"duration": 2427,
"game_mode": 22,
"lobby_type": 7,
"hero_id": 74,
"start_time": 1577230657,
"version": null,
"kills": 7,
"deaths": 8,
"assists": 9,
"skill": 3,
"xp_per_min": 524,
"gold_per_min": 314,
"hero_damage": 21499,
"tower_damage": 0,
"hero_healing": 0,
"last_hits": 93,
"lane": null,
"lane_role": null,
"is_roaming": null,
"cluster": 188,
"leaver_status": 0,
"party_size": null
},
{
"match_id": 5168259245,
"player_slot": 3,
"radiant_win": true,
"duration": 2490,
"game_mode": 22,
"lobby_type": 7,
"hero_id": 74,
"start_time": 1577227577,
"version": 21,
"kills": 5,
"deaths": 5,
"assists": 17,
"skill": 3,
"xp_per_min": 371,
"gold_per_min": 305,
"hero_damage": 16554,
"tower_damage": 152,
"hero_healing": 0,
"last_hits": 61,
"lane": 3,
"lane_role": 3,
"is_roaming": false,
"cluster": 185,
"leaver_status": 0,
"party_size": null
},
{
"match_id": 5168224768,
"player_slot": 1,
"radiant_win": true,
"duration": 2537,
"game_mode": 22,
"lobby_type": 7,
"hero_id": 26,
"start_time": 1577224296,
"version": null,
"kills": 11,
"deaths": 11,
"assists": 18,
"skill": 3,
"xp_per_min": 631,
"gold_per_min": 423,
"hero_damage": 16918,
"tower_damage": 182,
"hero_healing": 0,
"last_hits": 77,
"lane": null,
"lane_role": null,
"is_roaming": null,
"cluster": 134,
"leaver_status": 0,
"party_size": null
},
{
"match_id": 5166971784,
"player_slot": 4,
"radiant_win": true,
"duration": 2412,
"game_mode": 22,
"lobby_type": 7,
"hero_id": 15,
"start_time": 1577143770,
"version": null,
"kills": 11,
"deaths": 9,
"assists": 16,
"skill": 3,
"xp_per_min": 709,
"gold_per_min": 475,
"hero_damage": 39236,
"tower_damage": 5063,
"hero_healing": 0,
"last_hits": 187,
"lane": null,
"lane_role": null,
"is_roaming": null,
"cluster": 131,
"leaver_status": 0,
"party_size": null
},
{
"match_id": 5166936999,
"player_slot": 132,
"radiant_win": false,
"duration": 3058,
"game_mode": 22,
"lobby_type": 7,
"hero_id": 47,
"start_time": 1577140015,
"version": null,
"kills": 12,
"deaths": 12,
"assists": 10,
"skill": 2,
"xp_per_min": 579,
"gold_per_min": 439,
"hero_damage": 30669,
"tower_damage": 1724,
"hero_healing": 0,
"last_hits": 209,
"lane": null,
"lane_role": null,
"is_roaming": null,
"cluster": 133,
"leaver_status": 0,
"party_size": null
},
{
"match_id": 5166915036,
"player_slot": 3,
"radiant_win": true,
"duration": 1668,
"game_mode": 22,
"lobby_type": 7,
"hero_id": 74,
"start_time": 1577137925,
"version": null,
"kills": 5,
"deaths": 1,
"assists": 14,
"skill": 3,
"xp_per_min": 407,
"gold_per_min": 325,
"hero_damage": 11929,
"tower_damage": 2454,
"hero_healing": 240,
"last_hits": 36,
"lane": null,
"lane_role": null,
"is_roaming": null,
"cluster": 133,
"leaver_status": 0,
"party_size": null
},
{
"match_id": 5166887279,
"player_slot": 130,
"radiant_win": false,
"duration": 2107,
"game_mode": 22,
"lobby_type": 7,
"hero_id": 16,
"start_time": 1577135444,
"version": null,
"kills": 4,
"deaths": 3,
"assists": 18,
"skill": 3,
"xp_per_min": 553,
"gold_per_min": 400,
"hero_damage": 12727,
"tower_damage": 755,
"hero_healing": 135,
"last_hits": 176,
"lane": null,
"lane_role": null,
"is_roaming": null,
"cluster": 137,
"leaver_status": 0,
"party_size": null
},
{
"match_id": 5165677114,
"player_slot": 0,
"radiant_win": false,
"duration": 5184,
"game_mode": 22,
"lobby_type": 7,
"hero_id": 74,
"start_time": 1577057903,
"version": null,
"kills": 3,
"deaths": 12,
"assists": 22,
"skill": null,
"xp_per_min": 464,
"gold_per_min": 372,
"hero_damage": 53087,
"tower_damage": 649,
"hero_healing": 7573,
"last_hits": 209,
"lane": null,
"lane_role": null,
"is_roaming": null,
"cluster": 182,
"leaver_status": 0,
"party_size": null
},
{
"match_id": 5165648383,
"player_slot": 132,
"radiant_win": true,
"duration": 2462,
"game_mode": 22,
"lobby_type": 7,
"hero_id": 7,
"start_time": 1577054816,
"version": 21,
"kills": 4,
"deaths": 5,
"assists": 16,
"skill": 3,
"xp_per_min": 437,
"gold_per_min": 283,
"hero_damage": 19374,
"tower_damage": 164,
"hero_healing": 1475,
"last_hits": 88,
"lane": 1,
"lane_role": 3,
"is_roaming": false,
"cluster": 191,
"leaver_status": 0,
"party_size": null
},
{
"match_id": 5164193299,
"player_slot": 0,
"radiant_win": false,
"duration": 2808,
"game_mode": 22,
"lobby_type": 7,
"hero_id": 128,
"start_time": 1576970518,
"version": 21,
"kills": 4,
"deaths": 7,
"assists": 21,
"skill": 3,
"xp_per_min": 568,
"gold_per_min": 319,
"hero_damage": 17672,
"tower_damage": 771,
"hero_healing": 4160,
"last_hits": 74,
"lane": 1,
"lane_role": 1,
"is_roaming": false,
"cluster": 138,
"leaver_status": 0,
"party_size": null
},
{
"match_id": 5164172792,
"player_slot": 130,
"radiant_win": true,
"duration": 1585,
"game_mode": 22,
"lobby_type": 7,
"hero_id": 92,
"start_time": 1576968564,
"version": 21,
"kills": 3,
"deaths": 7,
"assists": 5,
"skill": 3,
"xp_per_min": 351,
"gold_per_min": 257,
"hero_damage": 9885,
"tower_damage": 587,
"hero_healing": 0,
"last_hits": 47,
"lane": 1,
"lane_role": 3,
"is_roaming": false,
"cluster": 183,
"leaver_status": 0,
"party_size": null
},
{
"match_id": 5164139296,
"player_slot": 0,
"radiant_win": false,
"duration": 2399,
"game_mode": 22,
"lobby_type": 7,
"hero_id": 7,
"start_time": 1576965714,
"version": null,
"kills": 2,
"deaths": 15,
"assists": 7,
"skill": 3,
"xp_per_min": 431,
"gold_per_min": 286,
"hero_damage": 14316,
"tower_damage": 0,
"hero_healing": 0,
"last_hits": 88,
"lane": null,
"lane_role": null,
"is_roaming": null,
"cluster": 186,
"leaver_status": 0,
"party_size": null
},
{
"match_id": 5164096173,
"player_slot": 129,
"radiant_win": true,
"duration": 1467,
"game_mode": 22,
"lobby_type": 7,
"hero_id": 14,
"start_time": 1576962448,
"version": null,
"kills": 2,
"deaths": 15,
"assists": 3,
"skill": 3,
"xp_per_min": 220,
"gold_per_min": 176,
"hero_damage": 5100,
"tower_damage": 0,
"hero_healing": 0,
"last_hits": 30,
"lane": null,
"lane_role": null,
"is_roaming": null,
"cluster": 182,
"leaver_status": 0,
"party_size": null
},
{
"match_id": 5164026000,
"player_slot": 0,
"radiant_win": true,
"duration": 2098,
"game_mode": 22,
"lobby_type": 7,
"hero_id": 74,
"start_time": 1576957808,
"version": null,
"kills": 5,
"deaths": 2,
"assists": 27,
"skill": 3,
"xp_per_min": 616,
"gold_per_min": 319,
"hero_damage": 15533,
"tower_damage": 2624,
"hero_healing": 12,
"last_hits": 54,
"lane": null,
"lane_role": null,
"is_roaming": null,
"cluster": 133,
"leaver_status": 0,
"party_size": null
},
{
"match_id": 5162715593,
"player_slot": 2,
"radiant_win": false,
"duration": 2081,
"game_mode": 22,
"lobby_type": 7,
"hero_id": 26,
"start_time": 1576883604,
"version": null,
"kills": 3,
"deaths": 7,
"assists": 7,
"skill": 3,
"xp_per_min": 325,
"gold_per_min": 227,
"hero_damage": 6714,
"tower_damage": 137,
"hero_healing": 400,
"last_hits": 29,
"lane": null,
"lane_role": null,
"is_roaming": null,
"cluster": 181,
"leaver_status": 0,
"party_size": null
},
{
"match_id": 5162693796,
"player_slot": 129,
"radiant_win": false,
"duration": 1806,
"game_mode": 22,
"lobby_type": 7,
"hero_id": 74,
"start_time": 1576881410,
"version": null,
"kills": 5,
"deaths": 0,
"assists": 16,
"skill": 3,
"xp_per_min": 480,
"gold_per_min": 357,
"hero_damage": 14620,
"tower_damage": 1786,
"hero_healing": 0,
"last_hits": 44,
"lane": null,
"lane_role": null,
"is_roaming": null,
"cluster": 135,
"leaver_status": 0,
"party_size": null
},
{
"match_id": 5161286227,
"player_slot": 3,
"radiant_win": false,
"duration": 2880,
"game_mode": 22,
"lobby_type": 7,
"hero_id": 98,
"start_time": 1576784413,
"version": null,
"kills": 10,
"deaths": 6,
"assists": 13,
"skill": 2,
"xp_per_min": 635,
"gold_per_min": 407,
"hero_damage": 25183,
"tower_damage": 423,
"hero_healing": 2020,
"last_hits": 251,
"lane": null,
"lane_role": null,
"is_roaming": null,
"cluster": 131,
"leaver_status": 0,
"party_size": 3
},
{
"match_id": 5161231812,
"player_slot": 132,
"radiant_win": false,
"duration": 2083,
"game_mode": 22,
"lobby_type": 7,
"hero_id": 74,
"start_time": 1576780807,
"version": null,
"kills": 13,
"deaths": 3,
"assists": 19,
"skill": 3,
"xp_per_min": 840,
"gold_per_min": 408,
"hero_damage": 38908,
"tower_damage": 1792,
"hero_healing": 240,
"last_hits": 71,
"lane": null,
"lane_role": null,
"is_roaming": null,
"cluster": 188,
"leaver_status": 0,
"party_size": null
},
{
"match_id": 5161174595,
"player_slot": 132,
"radiant_win": true,
"duration": 2620,
"game_mode": 22,
"lobby_type": 7,
"hero_id": 98,
"start_time": 1576777291,
"version": null,
"kills": 15,
"deaths": 11,
"assists": 11,
"skill": 3,
"xp_per_min": 723,
"gold_per_min": 373,
"hero_damage": 44924,
"tower_damage": 254,
"hero_healing": 0,
"last_hits": 121,
"lane": null,
"lane_role": null,
"is_roaming": null,
"cluster": 193,
"leaver_status": 0,
"party_size": null
},
{
"match_id": 5160198256,
"player_slot": 130,
"radiant_win": true,
"duration": 1803,
"game_mode": 22,
"lobby_type": 7,
"hero_id": 26,
"start_time": 1576711740,
"version": 21,
"kills": 2,
"deaths": 11,
"assists": 3,
"skill": 3,
"xp_per_min": 280,
"gold_per_min": 193,
"hero_damage": 5827,
"tower_damage": 20,
"hero_healing": 0,
"last_hits": 26,
"lane": 3,
"lane_role": 1,
"is_roaming": false,
"cluster": 131,
"leaver_status": 0,
"party_size": 1
}
]
